socmed_reporter/app.py
socmed_reporter-0.0.2.dist-info/LICENSE
socmed_reporter-0.0.2.dist-info/METADATA
socmed_reporter-0.0.2.dist-info/WHEEL
socmed_reporter-0.0.2.dist-info/top_level.txt
socmed_reporter-0.0.2.dist-info/RECORD
